lakewatch/__init__.py
lakewatch/auth/__init__.py
lakewatch/auth/auth.py
lakewatch/client.py
lakewatch/conn/__init__.py
lakewatch/conn/client_identifier.py
lakewatch/conn/conn.py
lakewatch/errors/__init__.py
lakewatch/errors/errors.py
lakewatch/exec_rule.py
lakewatch/helpers.py
lakewatch/preset_development/__init__.py
lakewatch/preset_development/errors.py
lakewatch/preset_development/preview_engine.py
lakewatch/preset_development/preview_parameters.py
lakewatch/preset_development/stage.py
lakewatch/types/__init__.py
lakewatch/types/content.py
lakewatch/types/datasource.py
lakewatch/types/dbui.py
lakewatch/types/helpers.py
lakewatch/types/rule.py
lakewatch/types/types.py
lakewatch/types/workspace_config.py
lakewatch-0.1.1.dist-info/WHEEL
lakewatch-0.1.1.dist-info/METADATA
lakewatch-0.1.1.dist-info/RECORD
