Metadata-Version: 2.1
Name: lakewatch
Requires-Dist: urllib3>=2.1.0,<3.0.0
Requires-Dist: lakewatch_api==0.1.1
Requires-Dist: databricks-sdk>=0.41.0
Requires-Dist: pydantic>=2
Requires-Dist: typing_extensions>=4.10.0
Requires-Dist: pyyaml==6.0.2
Version: 0.1.1
